{"v":3,"stories":{"components-button--docs":{"id":"components-button--docs","title":"Components/Button","name":"Docs","importPath":"./src/components/Button/Button.stories.tsx","tags":["autodocs","docs"],"storiesImports":[],"kind":"Components/Button","story":"Docs","parameters":{"__id":"components-button--docs","docsOnly":true,"fileName":"./src/components/Button/Button.stories.tsx"}},"components-button--primary":{"id":"components-button--primary","name":"Primary","title":"Components/Button","importPath":"./src/components/Button/Button.stories.tsx","tags":["autodocs","story"],"kind":"Components/Button","story":"Primary","parameters":{"__id":"components-button--primary","docsOnly":false,"fileName":"./src/components/Button/Button.stories.tsx"}},"components-button--reset":{"id":"components-button--reset","name":"Reset","title":"Components/Button","importPath":"./src/components/Button/Button.stories.tsx","tags":["autodocs","story"],"kind":"Components/Button","story":"Reset","parameters":{"__id":"components-button--reset","docsOnly":false,"fileName":"./src/components/Button/Button.stories.tsx"}},"components-button--large":{"id":"components-button--large","name":"Large","title":"Components/Button","importPath":"./src/components/Button/Button.stories.tsx","tags":["autodocs","story"],"kind":"Components/Button","story":"Large","parameters":{"__id":"components-button--large","docsOnly":false,"fileName":"./src/components/Button/Button.stories.tsx"}},"components-button--small":{"id":"components-button--small","name":"Small","title":"Components/Button","importPath":"./src/components/Button/Button.stories.tsx","tags":["autodocs","story"],"kind":"Components/Button","story":"Small","parameters":{"__id":"components-button--small","docsOnly":false,"fileName":"./src/components/Button/Button.stories.tsx"}},"components-basiccalendar--docs":{"id":"components-basiccalendar--docs","title":"Components/BasicCalendar","name":"Docs","importPath":"./src/components/Calendar/BasicCalendar.stories.tsx","tags":["autodocs","docs"],"storiesImports":[],"kind":"Components/BasicCalendar","story":"Docs","parameters":{"__id":"components-basiccalendar--docs","docsOnly":true,"fileName":"./src/components/Calendar/BasicCalendar.stories.tsx"}},"components-basiccalendar--preview-calendar":{"id":"components-basiccalendar--preview-calendar","name":"Preview Calendar","title":"Components/BasicCalendar","importPath":"./src/components/Calendar/BasicCalendar.stories.tsx","tags":["autodocs","story"],"kind":"Components/BasicCalendar","story":"Preview Calendar","parameters":{"__id":"components-basiccalendar--preview-calendar","docsOnly":false,"fileName":"./src/components/Calendar/BasicCalendar.stories.tsx"}},"components-basiccalendar--filter-calendar":{"id":"components-basiccalendar--filter-calendar","name":"Filter Calendar","title":"Components/BasicCalendar","importPath":"./src/components/Calendar/BasicCalendar.stories.tsx","tags":["autodocs","story"],"kind":"Components/BasicCalendar","story":"Filter Calendar","parameters":{"__id":"components-basiccalendar--filter-calendar","docsOnly":false,"fileName":"./src/components/Calendar/BasicCalendar.stories.tsx"}},"components-schedulecalendar--docs":{"id":"components-schedulecalendar--docs","title":"Components/ScheduleCalendar","name":"Docs","importPath":"./src/components/Calendar/ScheduleCalendar.stories.tsx","tags":["autodocs","docs"],"storiesImports":[],"kind":"Components/ScheduleCalendar","story":"Docs","parameters":{"__id":"components-schedulecalendar--docs","docsOnly":true,"fileName":"./src/components/Calendar/ScheduleCalendar.stories.tsx"}},"components-schedulecalendar--preview-calendar":{"id":"components-schedulecalendar--preview-calendar","name":"Preview Calendar","title":"Components/ScheduleCalendar","importPath":"./src/components/Calendar/ScheduleCalendar.stories.tsx","tags":["autodocs","story"],"kind":"Components/ScheduleCalendar","story":"Preview Calendar","parameters":{"__id":"components-schedulecalendar--preview-calendar","docsOnly":false,"fileName":"./src/components/Calendar/ScheduleCalendar.stories.tsx"}},"components-carousel--docs":{"id":"components-carousel--docs","title":"Components/Carousel","name":"Docs","importPath":"./src/components/Carousel/Carousel.stories.tsx","tags":["autodocs","docs"],"storiesImports":[],"kind":"Components/Carousel","story":"Docs","parameters":{"__id":"components-carousel--docs","docsOnly":true,"fileName":"./src/components/Carousel/Carousel.stories.tsx"}},"components-carousel--기본":{"id":"components-carousel--기본","name":"기본","title":"Components/Carousel","importPath":"./src/components/Carousel/Carousel.stories.tsx","tags":["autodocs","story"],"kind":"Components/Carousel","story":"기본","parameters":{"__id":"components-carousel--기본","docsOnly":false,"fileName":"./src/components/Carousel/Carousel.stories.tsx"}},"components-carousel--focus동작":{"id":"components-carousel--focus동작","name":"Focus동작","title":"Components/Carousel","importPath":"./src/components/Carousel/Carousel.stories.tsx","tags":["autodocs","story"],"kind":"Components/Carousel","story":"Focus동작","parameters":{"__id":"components-carousel--focus동작","docsOnly":false,"fileName":"./src/components/Carousel/Carousel.stories.tsx"}},"components-carousel--여러요소표시":{"id":"components-carousel--여러요소표시","name":"여러요소표시","title":"Components/Carousel","importPath":"./src/components/Carousel/Carousel.stories.tsx","tags":["autodocs","story"],"kind":"Components/Carousel","story":"여러요소표시","parameters":{"__id":"components-carousel--여러요소표시","docsOnly":false,"fileName":"./src/components/Carousel/Carousel.stories.tsx"}},"components-carousel--class-card사용":{"id":"components-carousel--class-card사용","name":"Class Card사용","title":"Components/Carousel","importPath":"./src/components/Carousel/Carousel.stories.tsx","tags":["autodocs","story"],"kind":"Components/Carousel","story":"Class Card사용","parameters":{"__id":"components-carousel--class-card사용","docsOnly":false,"fileName":"./src/components/Carousel/Carousel.stories.tsx"}},"components-classcard--docs":{"id":"components-classcard--docs","title":"Components/ClassCard","name":"Docs","importPath":"./src/components/ClassCard/ClassCard.stories.tsx","tags":["autodocs","docs"],"storiesImports":[],"kind":"Components/ClassCard","story":"Docs","parameters":{"__id":"components-classcard--docs","docsOnly":true,"fileName":"./src/components/ClassCard/ClassCard.stories.tsx"}},"components-classcard--모집중":{"id":"components-classcard--모집중","name":"모집중","title":"Components/ClassCard","importPath":"./src/components/ClassCard/ClassCard.stories.tsx","tags":["autodocs","story"],"kind":"Components/ClassCard","story":"모집중","parameters":{"__id":"components-classcard--모집중","docsOnly":false,"fileName":"./src/components/ClassCard/ClassCard.stories.tsx"}},"components-classcard--마감임박":{"id":"components-classcard--마감임박","name":"마감임박","title":"Components/ClassCard","importPath":"./src/components/ClassCard/ClassCard.stories.tsx","tags":["autodocs","story"],"kind":"Components/ClassCard","story":"마감임박","parameters":{"__id":"components-classcard--마감임박","docsOnly":false,"fileName":"./src/components/ClassCard/ClassCard.stories.tsx"}},"components-classcard--마감":{"id":"components-classcard--마감","name":"마감","title":"Components/ClassCard","importPath":"./src/components/ClassCard/ClassCard.stories.tsx","tags":["autodocs","story"],"kind":"Components/ClassCard","story":"마감","parameters":{"__id":"components-classcard--마감","docsOnly":false,"fileName":"./src/components/ClassCard/ClassCard.stories.tsx"}},"components-filters--docs":{"id":"components-filters--docs","title":"Components/Filters","name":"Docs","importPath":"./src/components/Filter/Filters.stories.tsx","tags":["autodocs","docs"],"storiesImports":[],"kind":"Components/Filters","story":"Docs","parameters":{"__id":"components-filters--docs","docsOnly":true,"fileName":"./src/components/Filter/Filters.stories.tsx"}},"components-filters--default":{"id":"components-filters--default","name":"Default","title":"Components/Filters","importPath":"./src/components/Filter/Filters.stories.tsx","tags":["autodocs","story"],"kind":"Components/Filters","story":"Default","parameters":{"__id":"components-filters--default","docsOnly":false,"fileName":"./src/components/Filter/Filters.stories.tsx"}},"components-instructorcard--docs":{"id":"components-instructorcard--docs","title":"Components/InstructorCard","name":"Docs","importPath":"./src/components/InstructorCard/InstructorCard.stories.tsx","tags":["autodocs","docs"],"storiesImports":[],"kind":"Components/InstructorCard","story":"Docs","parameters":{"__id":"components-instructorcard--docs","docsOnly":true,"fileName":"./src/components/InstructorCard/InstructorCard.stories.tsx"}},"components-instructorcard--기본":{"id":"components-instructorcard--기본","name":"기본","title":"Components/InstructorCard","importPath":"./src/components/InstructorCard/InstructorCard.stories.tsx","tags":["autodocs","story"],"kind":"Components/InstructorCard","story":"기본","parameters":{"__id":"components-instructorcard--기본","docsOnly":false,"fileName":"./src/components/InstructorCard/InstructorCard.stories.tsx"}},"components-map--docs":{"id":"components-map--docs","title":"Components/Map","name":"Docs","importPath":"./src/components/Map/Map.stories.tsx","tags":["autodocs","docs"],"storiesImports":[],"kind":"Components/Map","story":"Docs","parameters":{"__id":"components-map--docs","docsOnly":true,"fileName":"./src/components/Map/Map.stories.tsx"}},"components-map--기본":{"id":"components-map--기본","name":"기본","title":"Components/Map","importPath":"./src/components/Map/Map.stories.tsx","tags":["autodocs","story"],"kind":"Components/Map","story":"기본","parameters":{"__id":"components-map--기본","docsOnly":false,"fileName":"./src/components/Map/Map.stories.tsx"}},"components-rating--docs":{"id":"components-rating--docs","title":"Components/Rating","name":"Docs","importPath":"./src/components/Review/Rating.stories.tsx","tags":["autodocs","docs"],"storiesImports":[],"kind":"Components/Rating","story":"Docs","parameters":{"__id":"components-rating--docs","docsOnly":true,"fileName":"./src/components/Review/Rating.stories.tsx"}},"components-rating--default":{"id":"components-rating--default","name":"Default","title":"Components/Rating","importPath":"./src/components/Review/Rating.stories.tsx","tags":["autodocs","story"],"kind":"Components/Rating","story":"Default","parameters":{"__id":"components-rating--default","docsOnly":false,"fileName":"./src/components/Review/Rating.stories.tsx"}},"components-review--docs":{"id":"components-review--docs","title":"Components/Review","name":"Docs","importPath":"./src/components/Review/Review.stories.tsx","tags":["autodocs","docs"],"storiesImports":[],"kind":"Components/Review","story":"Docs","parameters":{"__id":"components-review--docs","docsOnly":true,"fileName":"./src/components/Review/Review.stories.tsx"}},"components-review--default":{"id":"components-review--default","name":"Default","title":"Components/Review","importPath":"./src/components/Review/Review.stories.tsx","tags":["autodocs","story"],"kind":"Components/Review","story":"Default","parameters":{"__id":"components-review--default","docsOnly":false,"fileName":"./src/components/Review/Review.stories.tsx"}},"components-review--int":{"id":"components-review--int","name":"Int","title":"Components/Review","importPath":"./src/components/Review/Review.stories.tsx","tags":["autodocs","story"],"kind":"Components/Review","story":"Int","parameters":{"__id":"components-review--int","docsOnly":false,"fileName":"./src/components/Review/Review.stories.tsx"}},"components-review--double":{"id":"components-review--double","name":"Double","title":"Components/Review","importPath":"./src/components/Review/Review.stories.tsx","tags":["autodocs","story"],"kind":"Components/Review","story":"Double","parameters":{"__id":"components-review--double","docsOnly":false,"fileName":"./src/components/Review/Review.stories.tsx"}},"components-reviewcomment--docs":{"id":"components-reviewcomment--docs","title":"Components/ReviewComment","name":"Docs","importPath":"./src/components/Review/ReviewComment.stories.tsx","tags":["autodocs","docs"],"storiesImports":[],"kind":"Components/ReviewComment","story":"Docs","parameters":{"__id":"components-reviewcomment--docs","docsOnly":true,"fileName":"./src/components/Review/ReviewComment.stories.tsx"}},"components-reviewcomment--default":{"id":"components-reviewcomment--default","name":"Default","title":"Components/ReviewComment","importPath":"./src/components/Review/ReviewComment.stories.tsx","tags":["autodocs","story"],"kind":"Components/ReviewComment","story":"Default","parameters":{"__id":"components-reviewcomment--default","docsOnly":false,"fileName":"./src/components/Review/ReviewComment.stories.tsx"}},"components-sharing--docs":{"id":"components-sharing--docs","title":"Components/Sharing","name":"Docs","importPath":"./src/components/Sharing/Sharing.stories.tsx","tags":["autodocs","docs"],"storiesImports":[],"kind":"Components/Sharing","story":"Docs","parameters":{"__id":"components-sharing--docs","docsOnly":true,"fileName":"./src/components/Sharing/Sharing.stories.tsx"}},"components-sharing--class":{"id":"components-sharing--class","name":"Class","title":"Components/Sharing","importPath":"./src/components/Sharing/Sharing.stories.tsx","tags":["autodocs","story"],"kind":"Components/Sharing","story":"Class","parameters":{"__id":"components-sharing--class","docsOnly":false,"fileName":"./src/components/Sharing/Sharing.stories.tsx"}},"components-sharing--instructor":{"id":"components-sharing--instructor","name":"Instructor","title":"Components/Sharing","importPath":"./src/components/Sharing/Sharing.stories.tsx","tags":["autodocs","story"],"kind":"Components/Sharing","story":"Instructor","parameters":{"__id":"components-sharing--instructor","docsOnly":false,"fileName":"./src/components/Sharing/Sharing.stories.tsx"}},"components-validationmessage--docs":{"id":"components-validationmessage--docs","title":"Components/ValidationMessage","name":"Docs","importPath":"./src/components/ValidationMessage/ValidationMessage.stories.tsx","tags":["autodocs","docs"],"storiesImports":[],"kind":"Components/ValidationMessage","story":"Docs","parameters":{"__id":"components-validationmessage--docs","docsOnly":true,"fileName":"./src/components/ValidationMessage/ValidationMessage.stories.tsx"}},"components-validationmessage--기본":{"id":"components-validationmessage--기본","name":"기본","title":"Components/ValidationMessage","importPath":"./src/components/ValidationMessage/ValidationMessage.stories.tsx","tags":["autodocs","story"],"kind":"Components/ValidationMessage","story":"기본","parameters":{"__id":"components-validationmessage--기본","docsOnly":false,"fileName":"./src/components/ValidationMessage/ValidationMessage.stories.tsx"}}}}
